emojitranslator/__init__.py
emojitranslator/data.py
emojitranslator/translator.py
emojitranslator-0.1.0.dist-info/licenses/LICENSE
emojitranslator-0.1.0.dist-info/METADATA
emojitranslator-0.1.0.dist-info/WHEEL
emojitranslator-0.1.0.dist-info/top_level.txt
emojitranslator-0.1.0.dist-info/RECORD
