Metadata-Version: 2.4
Name: emojitranslator
Version: 0.1.0
Summary: Translate text to emojis
Home-page: https://github.com/yourusername/emojitranslator
Author: Eldar Eliyev
Author-email: eldar2005matrix@gmail.com
License: MIT
Classifier: Programming Language :: Python :: 3
Classifier: License :: OSI Approved :: MIT License
Classifier: Operating System :: OS Independent
Requires-Python: >=3.10
License-File: LICENSE
Dynamic: author
Dynamic: author-email
Dynamic: classifier
Dynamic: description
Dynamic: description-content-type
Dynamic: home-page
Dynamic: license
Dynamic: license-file
Dynamic: requires-python
Dynamic: summary
